{"about.md":"8h11AeV6","api_index.md":"C5fjyYjO","api_setup.md":"OWp9VILK","guide_api-keys.md":"CS2fY1JT","guide_cli.md":"Bri8wGcY","guide_configuration.md":"BsqvtiRs","guide_developer-setup.md":"CmMTHY0H","guide_getting-started.md":"STOx0owK","guide_using-librislog_administration.md":"BQwGdfh7","guide_using-librislog_dashboard.md":"mr8P7-bM","guide_using-librislog_data-hygiene.md":"jyRFGZT3","guide_using-librislog_import-export.md":"DRhq0Auy","guide_using-librislog_library.md":"CkwLuNsc","guide_using-librislog_missing-covers.md":"C7-5BLla","guide_using-librislog_profile.md":"GUlmycKx","guide_using-librislog_progress.md":"BnVtM8xW","guide_using-librislog_statistics.md":"DiEVAl5P","index.md":"CWycEvas"}
